{
    "appid": "steam_546560",
    "game_name": "Half-Life: Alyx",
    "author_name": "vr-commiter",
    "desc": "Half-Life: Alyx TrueGear Suit Driver",
    "website": "https://github.com/vr-commiter/HLA_TrueGear",
    "readme_link": "https://github.com/vr-commiter/HLA_TrueGear/blob/master/README.md",
    "version_list": [
        {
            "date_updated": "",
            "download_link": "https://github.com/vr-commiter/HLA_TrueGear/releases/download/v0.1.0-beta/e3c0f7f68d0d12cc7a48618a746859ef.zip",
            "md5_value": "e3c0f7f68d0d12cc7a48618a746859ef",
            "version": "v0.1.0-beta",
            "status": "beta"
        }
    ]
}
